quasara_api_sdk/__init__.py
quasara_api_sdk/client.py
quasara_api-0.1.0.dist-info/METADATA
quasara_api-0.1.0.dist-info/WHEEL
quasara_api-0.1.0.dist-info/top_level.txt
quasara_api-0.1.0.dist-info/RECORD
