Metadata-Version: 2.4
Name: quasara-api
Version: 0.1.0
Summary: A Python SDK for interacting with the Quasara API
Author-email: Indrah Thelaganathan <indrah.thelaganathan@quasara.io>
Project-URL: Homepage, https://github.com/your-username/your-repo
Project-URL: Bug Tracker, https://github.com/your-username/your-repo/issues
Classifier: Programming Language :: Python :: 3
Classifier: License :: OSI Approved :: MIT License
Classifier: Operating System :: OS Independent
Classifier: Development Status :: 3 - Alpha
Classifier: Intended Audience :: Developers
Classifier: Topic :: Software Development :: Libraries
Requires-Python: >=3.8
Requires-Dist: requests>=2.20.0
